{
"type": "FeatureCollection",
"name": "hessian-spring",
"crs": { "type": "name", "properties": { "name": "urn:ogc:def:crs:OGC:1.3:CRS84" } },
"features": [
{ "type": "Feature", "properties": { "id": 1, "name": "Hessian Spring" }, "geometry": { "type": "Point", "coordinates": [ -73.9357, 40.85205 ] } }
]
}
